nbsphinx/__init__.py
nbsphinx/_static/nbsphinx-broken-thumbnail.svg
nbsphinx/_static/nbsphinx-code-cells.css_t
nbsphinx/_static/nbsphinx-gallery.css
nbsphinx/_static/nbsphinx-no-thumbnail.svg
nbsphinx/_texinputs/nbsphinx.sty
nbsphinx-0.9.4.dist-info/LICENSE
nbsphinx-0.9.4.dist-info/METADATA
nbsphinx-0.9.4.dist-info/WHEEL
nbsphinx-0.9.4.dist-info/top_level.txt
nbsphinx-0.9.4.dist-info/RECORD
