Metadata-Version: 2.1
Name: nbsphinx
Version: 0.9.4
Summary: Jupyter Notebook Tools for Sphinx
Home-page: https://nbsphinx.readthedocs.io/
Author: Matthias Geier
Author-email: Matthias.Geier@gmail.com
License: MIT
Project-URL: Documentation, https://nbsphinx.readthedocs.io/
Project-URL: Source Code, https://github.com/spatialaudio/nbsphinx/
Project-URL: Bug Tracker, https://github.com/spatialaudio/nbsphinx/issues/
Keywords: Sphinx,Jupyter,notebook
Platform: any
Classifier: Framework :: Sphinx
Classifier: Framework :: Sphinx :: Extension
Classifier: Framework :: Jupyter
Classifier: Intended Audience :: Education
Classifier: Intended Audience :: Science/Research
Classifier: License :: OSI Approved :: MIT License
Classifier: Operating System :: OS Independent
Classifier: Programming Language :: Python
Classifier: Programming Language :: Python :: 3
Classifier: Topic :: Documentation :: Sphinx
Requires-Python: >=3.6
License-File: LICENSE
Requires-Dist: docutils>=0.18.1
Requires-Dist: jinja2
Requires-Dist: nbconvert!=5.4,>=5.3
Requires-Dist: traitlets>=5
Requires-Dist: nbformat
Requires-Dist: sphinx>=1.8
